type_enforce/__init__.py
type_enforce/core.py
type_enforce/processors.py
type_enforce/utils.py
type_enforce-3.9.0.dist-info/LICENSE
type_enforce-3.9.0.dist-info/METADATA
type_enforce-3.9.0.dist-info/WHEEL
type_enforce-3.9.0.dist-info/top_level.txt
type_enforce-3.9.0.dist-info/RECORD
