Metadata-Version: 2.1
Name: type-enforce
Version: 3.9.0
Summary: Supports enforcing type annotations on functions and coroutines. Complete support for types from typing module.
Home-page: https://github.com/AceExpert/type-enforce-py
Author: Cybertron
License: Apache 2.0
Project-URL: Issue Tracker, https://github.com/AceExpert/type-enforce-py/issues
Project-URL: Contribute, https://github.com/AceExpert/type-enforce-py/pulls
Platform: UNKNOWN
Classifier: Development Status :: 5 - Production/Stable
Classifier: License :: OSI Approved :: Apache Software License
Classifier: Intended Audience :: Developers
Classifier: Natural Language :: English
Classifier: Operating System :: OS Independent
Classifier: Programming Language :: Python :: 3
Classifier: Programming Language :: Python :: 3.8
Classifier: Topic :: Software Development :: Libraries
Classifier: Topic :: Software Development :: Libraries :: Python Modules
Classifier: Topic :: Utilities
Classifier: Typing :: Typed
Requires-Python: >=3.0.0,<3.9.5
License-File: LICENSE
